{
  "appInfo" : {
    "build" : "213.6777.52",
    "buildDate" : "2022-01-28T03:47:48.092Z[UTC]",
    "productCode" : "IC",
    "generated" : "2023-03-29T12:10:48.513433Z",
    "os" : "macOS 13.2.1",
    "runtime" : "JetBrains s.r.o. 11.0.13 11.0.13+7-b1751.25"
  },
  "runtimeInfo" : {
    "maxMemory" : 788529152,
    "numberOfProcessors" : 8,
    "maxNumberOfIndexingThreads" : 4,
    "maxSizeOfFileForIntelliSense" : 2560000,
    "maxSizeOfFileForContentLoading" : 20971520
  },
  "projectIndexingHistory" : {
    "projectName" : "flutter_dojo-master",
    "times" : {
      "indexingReason" : "On project open",
      "wasFullIndexing" : true,
      "totalUpdatingTime" : 618814709,
      "indexingTime" : 152241000,
      "contentLoadingTime" : 11898727,
      "scanFilesTime" : 353306000,
      "pushPropertiesTime" : 2548000,
      "indexExtensionsTime" : 0,
      "updatingStart" : "2023-03-29T12:10:47.889501Z",
      "updatingEnd" : "2023-03-29T12:10:48.510012Z",
      "totalSuspendedTime" : 0,
      "wasInterrupted" : false
    },
    "fileCount" : {
      "numberOfFileProviders" : 10,
      "numberOfScannedFiles" : 5101,
      "numberOfFilesIndexedByInfrastructureExtensionsDuringScan" : 0,
      "numberOfFilesScheduledForIndexingAfterScan" : 1,
      "numberOfFilesIndexedByInfrastructureExtensionsDuringIndexingStage" : 0,
      "numberOfFilesIndexedWithLoadingContent" : 1
    },
    "totalStatsPerFileType" : [ {
      "fileType" : "Dart",
      "partOfTotalProcessingTime" : {
        "part" : 139429292,
        "total" : 139429292
      },
      "partOfTotalContentLoadingTime" : {
        "part" : 11603584,
        "total" : 11603584
      },
      "totalNumberOfFiles" : 1,
      "totalFilesSize" : 9195,
      "indexingSpeed" : {
        "totalBytes" : 9195,
        "totalTime" : 139429292
      },
      "biggestContributors" : [ {
        "providerName" : "Module 'flutter_dojo-master' (flutter_dojo-master)",
        "numberOfFiles" : 1,
        "totalFilesSize" : 9195,
        "partOfTotalProcessingTimeOfThisFileType" : {
          "part" : 139429292,
          "total" : 139429292
        }
      } ]
    } ],
    "totalStatsPerIndexer" : [ {
      "indexId" : "TodoIndex",
      "partOfTotalIndexingTime" : {
        "part" : 40116709,
        "total" : 94041626
      },
      "totalNumberOfFiles" : 1,
      "totalNumberOfFilesIndexedByExtensions" : 0,
      "totalFilesSize" : 9195,
      "indexingSpeed" : {
        "totalBytes" : 9195,
        "totalTime" : 40116709
      },
      "snapshotInputMappingStats" : {
        "totalRequests" : 0,
        "totalMisses" : 0,
        "totalHits" : 0
      }
    }, {
      "indexId" : "DartImportIndex",
      "partOfTotalIndexingTime" : {
        "part" : 18704458,
        "total" : 94041626
      },
      "totalNumberOfFiles" : 1,
      "totalNumberOfFilesIndexedByExtensions" : 0,
      "totalFilesSize" : 9195,
      "indexingSpeed" : {
        "totalBytes" : 9195,
        "totalTime" : 18704458
      },
      "snapshotInputMappingStats" : {
        "totalRequests" : 0,
        "totalMisses" : 0,
        "totalHits" : 0
      }
    }, {
      "indexId" : "IdIndex",
      "partOfTotalIndexingTime" : {
        "part" : 15479958,
        "total" : 94041626
      },
      "totalNumberOfFiles" : 1,
      "totalNumberOfFilesIndexedByExtensions" : 0,
      "totalFilesSize" : 9195,
      "indexingSpeed" : {
        "totalBytes" : 9195,
        "totalTime" : 15479958
      },
      "snapshotInputMappingStats" : {
        "totalRequests" : 0,
        "totalMisses" : 0,
        "totalHits" : 0
      }
    }, {
      "indexId" : "Trigram.Index",
      "partOfTotalIndexingTime" : {
        "part" : 9268334,
        "total" : 94041626
      },
      "totalNumberOfFiles" : 1,
      "totalNumberOfFilesIndexedByExtensions" : 0,
      "totalFilesSize" : 9195,
      "indexingSpeed" : {
        "totalBytes" : 9195,
        "totalTime" : 9268334
      },
      "snapshotInputMappingStats" : {
        "totalRequests" : 0,
        "totalMisses" : 0,
        "totalHits" : 0
      }
    }, {
      "indexId" : "DartComponentIndex",
      "partOfTotalIndexingTime" : {
        "part" : 7942042,
        "total" : 94041626
      },
      "totalNumberOfFiles" : 1,
      "totalNumberOfFilesIndexedByExtensions" : 0,
      "totalFilesSize" : 9195,
      "indexingSpeed" : {
        "totalBytes" : 9195,
        "totalTime" : 7942042
      },
      "snapshotInputMappingStats" : {
        "totalRequests" : 0,
        "totalMisses" : 0,
        "totalHits" : 0
      }
    }, {
      "indexId" : "DartPathIndex",
      "partOfTotalIndexingTime" : {
        "part" : 668458,
        "total" : 94041626
      },
      "totalNumberOfFiles" : 1,
      "totalNumberOfFilesIndexedByExtensions" : 0,
      "totalFilesSize" : 9195,
      "indexingSpeed" : {
        "totalBytes" : 9195,
        "totalTime" : 668458
      },
      "snapshotInputMappingStats" : {
        "totalRequests" : 0,
        "totalMisses" : 0,
        "totalHits" : 0
      }
    }, {
      "indexId" : "DartClassIndex",
      "partOfTotalIndexingTime" : {
        "part" : 645208,
        "total" : 94041626
      },
      "totalNumberOfFiles" : 1,
      "totalNumberOfFilesIndexedByExtensions" : 0,
      "totalFilesSize" : 9195,
      "indexingSpeed" : {
        "totalBytes" : 9195,
        "totalTime" : 645208
      },
      "snapshotInputMappingStats" : {
        "totalRequests" : 0,
        "totalMisses" : 0,
        "totalHits" : 0
      }
    }, {
      "indexId" : "DartLibraryIndex",
      "partOfTotalIndexingTime" : {
        "part" : 622292,
        "total" : 94041626
      },
      "totalNumberOfFiles" : 1,
      "totalNumberOfFilesIndexedByExtensions" : 0,
      "totalFilesSize" : 9195,
      "indexingSpeed" : {
        "totalBytes" : 9195,
        "totalTime" : 622292
      },
      "snapshotInputMappingStats" : {
        "totalRequests" : 0,
        "totalMisses" : 0,
        "totalHits" : 0
      }
    }, {
      "indexId" : "DartSymbolIndex",
      "partOfTotalIndexingTime" : {
        "part" : 594167,
        "total" : 94041626
      },
      "totalNumberOfFiles" : 1,
      "totalNumberOfFilesIndexedByExtensions" : 0,
      "totalFilesSize" : 9195,
      "indexingSpeed" : {
        "totalBytes" : 9195,
        "totalTime" : 594167
      },
      "snapshotInputMappingStats" : {
        "totalRequests" : 0,
        "totalMisses" : 0,
        "totalHits" : 0
      }
    } ],
    "scanningStatistics" : [ {
      "providerName" : "Library Dart Packages",
      "numberOfScannedFiles" : 2949,
      "numberOfSkippedFiles" : 16,
      "numberOfFilesForIndexing" : 0,
      "numberOfFilesFullyIndexedByInfrastructureExtensions" : 0,
      "scanningTime" : 172271955,
      "timeProcessingUpToDateFiles" : 0,
      "timeUpdatingContentLessIndexes" : 6731116,
      "timeIndexingWithoutContent" : 0
    }, {
      "providerName" : "Library Flutter Plugins",
      "numberOfScannedFiles" : 1086,
      "numberOfSkippedFiles" : 0,
      "numberOfFilesForIndexing" : 0,
      "numberOfFilesFullyIndexedByInfrastructureExtensions" : 0,
      "scanningTime" : 133677578,
      "timeProcessingUpToDateFiles" : 0,
      "timeUpdatingContentLessIndexes" : 3969213,
      "timeIndexingWithoutContent" : 0
    }, {
      "providerName" : "Module 'flutter_dojo-master' (flutter_dojo-master)",
      "numberOfScannedFiles" : 670,
      "numberOfSkippedFiles" : 0,
      "numberOfFilesForIndexing" : 1,
      "numberOfFilesFullyIndexedByInfrastructureExtensions" : 0,
      "scanningTime" : 117419755,
      "timeProcessingUpToDateFiles" : 0,
      "timeUpdatingContentLessIndexes" : 17329804,
      "timeIndexingWithoutContent" : 3345583
    }, {
      "providerName" : "Library Dart SDK",
      "numberOfScannedFiles" : 172,
      "numberOfSkippedFiles" : 0,
      "numberOfFilesForIndexing" : 0,
      "numberOfFilesFullyIndexedByInfrastructureExtensions" : 0,
      "scanningTime" : 57354838,
      "timeProcessingUpToDateFiles" : 0,
      "timeUpdatingContentLessIndexes" : 1119035,
      "timeIndexingWithoutContent" : 0
    }, {
      "providerName" : "Indexable set contributor 'com.intellij.javaee.ExternalResourcesRootsProvider@739419ea' (non-project)",
      "numberOfScannedFiles" : 224,
      "numberOfSkippedFiles" : 4,
      "numberOfFilesForIndexing" : 0,
      "numberOfFilesFullyIndexedByInfrastructureExtensions" : 0,
      "scanningTime" : 54138593,
      "timeProcessingUpToDateFiles" : 0,
      "timeUpdatingContentLessIndexes" : 1147458,
      "timeIndexingWithoutContent" : 0
    }, {
      "providerName" : "Indexable set contributor 'Scratches & Consoles' (project)",
      "numberOfScannedFiles" : 0,
      "numberOfSkippedFiles" : 0,
      "numberOfFilesForIndexing" : 0,
      "numberOfFilesFullyIndexedByInfrastructureExtensions" : 0,
      "scanningTime" : 0,
      "timeProcessingUpToDateFiles" : 0,
      "timeUpdatingContentLessIndexes" : 0,
      "timeIndexingWithoutContent" : 0
    }, {
      "providerName" : "Indexable set contributor 'com.intellij.javaee.ExternalResourcesRootsProvider@739419ea' (project)",
      "numberOfScannedFiles" : 0,
      "numberOfSkippedFiles" : 0,
      "numberOfFilesForIndexing" : 0,
      "numberOfFilesFullyIndexedByInfrastructureExtensions" : 0,
      "scanningTime" : 0,
      "timeProcessingUpToDateFiles" : 0,
      "timeUpdatingContentLessIndexes" : 0,
      "timeIndexingWithoutContent" : 0
    }, {
      "providerName" : "Indexable set contributor 'Scratches & Consoles' (non-project)",
      "numberOfScannedFiles" : 0,
      "numberOfSkippedFiles" : 0,
      "numberOfFilesForIndexing" : 0,
      "numberOfFilesFullyIndexedByInfrastructureExtensions" : 0,
      "scanningTime" : 0,
      "timeProcessingUpToDateFiles" : 0,
      "timeUpdatingContentLessIndexes" : 0,
      "timeIndexingWithoutContent" : 0
    }, {
      "providerName" : "Indexable set contributor 'Kotlin Script dependencies' (project)",
      "numberOfScannedFiles" : 0,
      "numberOfSkippedFiles" : 0,
      "numberOfFilesForIndexing" : 0,
      "numberOfFilesFullyIndexedByInfrastructureExtensions" : 0,
      "scanningTime" : 0,
      "timeProcessingUpToDateFiles" : 0,
      "timeUpdatingContentLessIndexes" : 0,
      "timeIndexingWithoutContent" : 0
    }, {
      "providerName" : "Indexable set contributor 'Kotlin Script dependencies' (non-project)",
      "numberOfScannedFiles" : 0,
      "numberOfSkippedFiles" : 0,
      "numberOfFilesForIndexing" : 0,
      "numberOfFilesFullyIndexedByInfrastructureExtensions" : 0,
      "scanningTime" : 0,
      "timeProcessingUpToDateFiles" : 0,
      "timeUpdatingContentLessIndexes" : 0,
      "timeIndexingWithoutContent" : 0
    } ],
    "fileProviderStatistics" : [ {
      "providerName" : "Module 'flutter_dojo-master' (flutter_dojo-master)",
      "totalNumberOfIndexedFiles" : 1,
      "totalNumberOfFilesFullyIndexedByExtensions" : 0,
      "totalIndexingTime" : 142975750,
      "contentLoadingTime" : 11898727,
      "numberOfTooLargeForIndexingFiles" : 0,
      "slowIndexedFiles" : [ ]
    } ]
  }
}